<?xml version="1.0" encoding="UTF-8"?>
<ti:app xmlns:ti="http://ti.appcelerator.org">
    <deployment-targets>
        <target device="mobileweb">false</target>
        <target device="iphone">false</target>
        <target device="ipad">false</target>
        <target device="android">true</target>
        <target device="blackberry">false</target>
    </deployment-targets>
    <sdk-version>2.0.2.GA</sdk-version>
    <id>com.tm.vanadium</id>
    <name>vanadium</name>
    <version>1.0</version>
    <publisher>thomas</publisher>
    <url>http://webappzone.de</url>
    <description>not specified</description>
    <copyright>2012 by thomas</copyright>
    <icon>appicon.png</icon>
    <persistent-wifi>false</persistent-wifi>
    <prerendered-icon>false</prerendered-icon>
    <statusbar-style>default</statusbar-style>
    <statusbar-hidden>false</statusbar-hidden>
    <fullscreen>false</fullscreen>
    <navbar-hidden>false</navbar-hidden>
    <analytics>true</analytics>
    <guid>d07f5365-73e1-4dd7-b8ab-21785b0ca793</guid>
    <property name="ti.ui.defaultunit">system</property>
    <property name="ti.android.bug2373.disableDetection" type="bool">true</property>
	<property name="ti.android.bug2373.restartDelay" type="int">500</property>
	<property name="ti.android.bug2373.finishDelay" type="int">0</property>
	<property name="ti.android.bug2373.skipAlert" type="bool">false</property>
	<property name="ti.android.bug2373.message">An application restart is required</property>
	<property name="ti.android.bug2373.title">Restart Required</property>
	<property name="ti.android.bug2373.buttonText">Continue</property>
    <iphone>
        <orientations device="iphone">
            <orientation>Ti.UI.PORTRAIT</orientation>
        </orientations>
        <orientations device="ipad">
            <orientation>Ti.UI.PORTRAIT</orientation>
            <orientation>Ti.UI.UPSIDE_PORTRAIT</orientation>
            <orientation>Ti.UI.LANDSCAPE_LEFT</orientation>
            <orientation>Ti.UI.LANDSCAPE_RIGHT</orientation>
        </orientations>
    </iphone>
    <android xmlns:android="http://schemas.android.com/apk/res/android"/>
    <mobileweb>
        <precache/>
        <splash>
            <enabled>true</enabled>
            <inline-css-images>true</inline-css-images>
        </splash>
        <theme>default</theme>
    </mobileweb>
    <modules/>
</ti:app>
